[{"_id": "1985", "CrimeTypes": [{"Victim Race": "Asian/Pacific Islander", "CountByRace": 254}, {"Victim Race": "White", "CountByRace": 10290}, {"Victim Race": "Native American/Alaska Native", "CountByRace": 135}, {"Victim Race": "Black", "CountByRace": 7611}, {"Victim Race": "Unknown", "CountByRace": 96}], "CountByRace": 18386},
{"_id": "1996", "CrimeTypes": [{"Victim Race": "Native American/Alaska Native", "CountByRace": 121}, {"Victim Race": "Asian/Pacific Islander", "CountByRace": 346}, {"Victim Race": "White", "CountByRace": 9294}, {"Victim Race": "Black", "CountByRace": 9049}, {"Victim Race": "Unknown", "CountByRace": 159}], "CountByRace": 18969},
{"_id": "1988", "CrimeTypes": [{"Victim Race": "Asian/Pacific Islander", "CountByRace": 186}, {"Victim Race": "Native American/Alaska Native", "CountByRace": 129}, {"Victim Race": "White", "CountByRace": 9355}, {"Victim Race": "Unknown", "CountByRace": 175}, {"Victim Race": "Black", "CountByRace": 8934}], "CountByRace": 18779},
{"_id": "2002", "CrimeTypes": [{"Victim Race": "White", "CountByRace": 7865}, {"Victim Race": "Native American/Alaska Native", "CountByRace": 129}, {"Victim Race": "Black", "CountByRace": 7771}, {"Victim Race": "Unknown", "CountByRace": 212}, {"Victim Race": "Asian/Pacific Islander", "CountByRace": 291}], "CountByRace": 16268},
{"_id": "2006", "CrimeTypes": [{"Victim Race": "Native American/Alaska Native", "CountByRace": 120}, {"Victim Race": "Unknown", "CountByRace": 213}, {"Victim Race": "White", "CountByRace": 8163}, {"Victim Race": "Black", "CountByRace": 8454}, {"Victim Race": "Asian/Pacific Islander", "CountByRace": 325}], "CountByRace": 17275},
{"_id": "2001", "CrimeTypes": [{"Victim Race": "Asian/Pacific Islander", "CountByRace": 299}, {"Victim Race": "Native American/Alaska Native", "CountByRace": 99}, {"Victim Race": "Black", "CountByRace": 7252}, {"Victim Race": "White", "CountByRace": 7962}, {"Victim Race": "Unknown", "CountByRace": 191}], "CountByRace": 15803},
{"_id": "1994", "CrimeTypes": [{"Victim Race": "Black", "CountByRace": 11723}, {"Victim Race": "Asian/Pacific Islander", "CountByRace": 393}, {"Victim Race": "Unknown", "CountByRace": 166}, {"Victim Race": "Native American/Alaska Native", "CountByRace": 139}, {"Victim Race": "White", "CountByRace": 10825}], "CountByRace": 23246},
{"_id": "1980", "CrimeTypes": [{"Victim Race": "Black", "CountByRace": 9842}, {"Victim Race": "White", "CountByRace": 12270}, {"Victim Race": "Asian/Pacific Islander", "CountByRace": 168}, {"Victim Race": "Unknown", "CountByRace": 658}, {"Victim Race": "Native American/Alaska Native", "CountByRace": 154}], "CountByRace": 23092},
{"_id": "2007", "CrimeTypes": [{"Victim Race": "Asian/Pacific Islander", "CountByRace": 281}, {"Victim Race": "Native American/Alaska Native", "CountByRace": 100}, {"Victim Race": "White", "CountByRace": 8172}, {"Victim Race": "Black", "CountByRace": 8502}, {"Victim Race": "Unknown", "CountByRace": 248}], "CountByRace": 17303},
{"_id": "2011", "CrimeTypes": [{"Victim Race": "Black", "CountByRace": 7246}, {"Victim Race": "Asian/Pacific Islander", "CountByRace": 263}, {"Victim Race": "Native American/Alaska Native", "CountByRace": 107}, {"Victim Race": "Unknown", "CountByRace": 185}, {"Victim Race": "White", "CountByRace": 6955}], "CountByRace": 14756},
{"_id": "2013", "CrimeTypes": [{"Victim Race": "Unknown", "CountByRace": 162}, {"Victim Race": "White", "CountByRace": 6713}, {"Victim Race": "Asian/Pacific Islander", "CountByRace": 241}, {"Victim Race": "Black", "CountByRace": 7226}, {"Victim Race": "Native American/Alaska Native", "CountByRace": 103}], "CountByRace": 14445},
{"_id": "2014", "CrimeTypes": [{"Victim Race": "Native American/Alaska Native", "CountByRace": 113}, {"Victim Race": "Asian/Pacific Islander", "CountByRace": 233}, {"Victim Race": "White", "CountByRace": 6701}, {"Victim Race": "Unknown", "CountByRace": 174}, {"Victim Race": "Black", "CountByRace": 7109}], "CountByRace": 14330},
{"_id": "1981", "CrimeTypes": [{"Victim Race": "Native American/Alaska Native", "CountByRace": 136}, {"Victim Race": "Unknown", "CountByRace": 134}, {"Victim Race": "Asian/Pacific Islander", "CountByRace": 191}, {"Victim Race": "White", "CountByRace": 11412}, {"Victim Race": "Black", "CountByRace": 9335}], "CountByRace": 21208},
{"_id": "2008", "CrimeTypes": [{"Victim Race": "Unknown", "CountByRace": 250}, {"Victim Race": "Native American/Alaska Native", "CountByRace": 113}, {"Victim Race": "Asian/Pacific Islander", "CountByRace": 217}, {"Victim Race": "Black", "CountByRace": 7449}, {"Victim Race": "White", "CountByRace": 7566}], "CountByRace": 15595},
{"_id": "2000", "CrimeTypes": [{"Victim Race": "Native American/Alaska Native", "CountByRace": 116}, {"Victim Race": "Unknown", "CountByRace": 174}, {"Victim Race": "Asian/Pacific Islander", "CountByRace": 249}, {"Victim Race": "Black", "CountByRace": 6921}, {"Victim Race": "White", "CountByRace": 7211}], "CountByRace": 14671},
{"_id": "1984", "CrimeTypes": [{"Victim Race": "Black", "CountByRace": 7420}, {"Victim Race": "White", "CountByRace": 10179}, {"Victim Race": "Asian/Pacific Islander", "CountByRace": 232}, {"Victim Race": "Native American/Alaska Native", "CountByRace": 126}, {"Victim Race": "Unknown", "CountByRace": 136}], "CountByRace": 18093},
{"_id": "2005", "CrimeTypes": [{"Victim Race": "Asian/Pacific Islander", "CountByRace": 306}, {"Victim Race": "Native American/Alaska Native", "CountByRace": 124}, {"Victim Race": "White", "CountByRace": 8132}, {"Victim Race": "Unknown", "CountByRace": 228}, {"Victim Race": "Black", "CountByRace": 8046}], "CountByRace": 16836},
{"_id": "1989", "CrimeTypes": [{"Victim Race": "Unknown", "CountByRace": 205}, {"Victim Race": "White", "CountByRace": 9617}, {"Victim Race": "Native American/Alaska Native", "CountByRace": 136}, {"Victim Race": "Black", "CountByRace": 9684}, {"Victim Race": "Asian/Pacific Islander", "CountByRace": 226}], "CountByRace": 19868},
{"_id": "2010", "CrimeTypes": [{"Victim Race": "White", "CountByRace": 7177}, {"Victim Race": "Black", "CountByRace": 7414}, {"Victim Race": "Unknown", "CountByRace": 170}, {"Victim Race": "Asian/Pacific Islander", "CountByRace": 244}, {"Victim Race": "Native American/Alaska Native", "CountByRace": 116}], "CountByRace": 15121},
{"_id": "1995", "CrimeTypes": [{"Victim Race": "Asian/Pacific Islander", "CountByRace": 408}, {"Victim Race": "White", "CountByRace": 10278}, {"Victim Race": "Unknown", "CountByRace": 200}, {"Victim Race": "Black", "CountByRace": 10133}, {"Victim Race": "Native American/Alaska Native", "CountByRace": 160}], "CountByRace": 21179},
{"_id": "2012", "CrimeTypes": [{"Victim Race": "Black", "CountByRace": 7475}, {"Victim Race": "Native American/Alaska Native", "CountByRace": 99}, {"Victim Race": "White", "CountByRace": 7036}, {"Victim Race": "Unknown", "CountByRace": 150}, {"Victim Race": "Asian/Pacific Islander", "CountByRace": 273}], "CountByRace": 15033},
{"_id": "1993", "CrimeTypes": [{"Victim Race": "Asian/Pacific Islander", "CountByRace": 449}, {"Victim Race": "Black", "CountByRace": 12269}, {"Victim Race": "Native American/Alaska Native", "CountByRace": 148}, {"Victim Race": "White", "CountByRace": 11260}, {"Victim Race": "Unknown", "CountByRace": 209}], "CountByRace": 24335},
{"_id": "1997", "CrimeTypes": [{"Victim Race": "Asian/Pacific Islander", "CountByRace": 342}, {"Victim Race": "Black", "CountByRace": 8497}, {"Victim Race": "White", "CountByRace": 8611}, {"Victim Race": "Unknown", "CountByRace": 205}, {"Victim Race": "Native American/Alaska Native", "CountByRace": 139}], "CountByRace": 17794},
{"_id": "1991", "CrimeTypes": [{"Victim Race": "Unknown", "CountByRace": 188}, {"Victim Race": "Native American/Alaska Native", "CountByRace": 144}, {"Victim Race": "Black", "CountByRace": 11190}, {"Victim Race": "White", "CountByRace": 10715}, {"Victim Race": "Asian/Pacific Islander", "CountByRace": 420}], "CountByRace": 22657},
{"_id": "2003", "CrimeTypes": [{"Victim Race": "Native American/Alaska Native", "CountByRace": 116}, {"Victim Race": "Asian/Pacific Islander", "CountByRace": 324}, {"Victim Race": "Black", "CountByRace": 7899}, {"Victim Race": "Unknown", "CountByRace": 217}, {"Victim Race": "White", "CountByRace": 7956}], "CountByRace": 16512},
{"_id": "1998", "CrimeTypes": [{"Victim Race": "Black", "CountByRace": 7358}, {"Victim Race": "Native American/Alaska Native", "CountByRace": 128}, {"Victim Race": "Asian/Pacific Islander", "CountByRace": 238}, {"Victim Race": "Unknown", "CountByRace": 226}, {"Victim Race": "White", "CountByRace": 8111}], "CountByRace": 16061},
{"_id": "1990", "CrimeTypes": [{"Victim Race": "White", "CountByRace": 10298}, {"Victim Race": "Native American/Alaska Native", "CountByRace": 139}, {"Victim Race": "Black", "CountByRace": 10344}, {"Victim Race": "Asian/Pacific Islander", "CountByRace": 221}, {"Victim Race": "Unknown", "CountByRace": 244}], "CountByRace": 21246},
{"_id": "1987", "CrimeTypes": [{"Victim Race": "Unknown", "CountByRace": 140}, {"Victim Race": "Native American/Alaska Native", "CountByRace": 141}, {"Victim Race": "White", "CountByRace": 9893}, {"Victim Race": "Asian/Pacific Islander", "CountByRace": 252}, {"Victim Race": "Black", "CountByRace": 8357}], "CountByRace": 18783},
{"_id": "1982", "CrimeTypes": [{"Victim Race": "White", "CountByRace": 11337}, {"Victim Race": "Asian/Pacific Islander", "CountByRace": 227}, {"Victim Race": "Black", "CountByRace": 8727}, {"Victim Race": "Unknown", "CountByRace": 91}, {"Victim Race": "Native American/Alaska Native", "CountByRace": 162}], "CountByRace": 20544},
{"_id": "1986", "CrimeTypes": [{"Victim Race": "White", "CountByRace": 10686}, {"Victim Race": "Unknown", "CountByRace": 102}, {"Victim Race": "Asian/Pacific Islander", "CountByRace": 296}, {"Victim Race": "Black", "CountByRace": 8869}, {"Victim Race": "Native American/Alaska Native", "CountByRace": 172}], "CountByRace": 20125},
{"_id": "2009", "CrimeTypes": [{"Victim Race": "Unknown", "CountByRace": 160}, {"Victim Race": "Native American/Alaska Native", "CountByRace": 119}, {"Victim Race": "Asian/Pacific Islander", "CountByRace": 282}, {"Victim Race": "White", "CountByRace": 7794}, {"Victim Race": "Black", "CountByRace": 7485}], "CountByRace": 15840},
{"_id": "1983", "CrimeTypes": [{"Victim Race": "Black", "CountByRace": 8374}, {"Victim Race": "White", "CountByRace": 10769}, {"Victim Race": "Asian/Pacific Islander", "CountByRace": 264}, {"Victim Race": "Unknown", "CountByRace": 92}, {"Victim Race": "Native American/Alaska Native", "CountByRace": 154}], "CountByRace": 19653},
{"_id": "1992", "CrimeTypes": [{"Victim Race": "Asian/Pacific Islander", "CountByRace": 410}, {"Victim Race": "Black", "CountByRace": 11705}, {"Victim Race": "White", "CountByRace": 11338}, {"Victim Race": "Unknown", "CountByRace": 180}, {"Victim Race": "Native American/Alaska Native", "CountByRace": 160}], "CountByRace": 23793},
{"_id": "2004", "CrimeTypes": [{"Victim Race": "Black", "CountByRace": 7612}, {"Victim Race": "Unknown", "CountByRace": 207}, {"Victim Race": "White", "CountByRace": 8011}, {"Victim Race": "Native American/Alaska Native", "CountByRace": 130}, {"Victim Race": "Asian/Pacific Islander", "CountByRace": 273}], "CountByRace": 16233},
{"_id": "1999", "CrimeTypes": [{"Victim Race": "White", "CountByRace": 7470}, {"Victim Race": "Black", "CountByRace": 6616}, {"Victim Race": "Native American/Alaska Native", "CountByRace": 140}, {"Victim Race": "Asian/Pacific Islander", "CountByRace": 266}, {"Victim Race": "Unknown", "CountByRace": 129}], "CountByRace": 14621},
]